xoq-0.2.0.dist-info/METADATA
xoq-0.2.0.dist-info/WHEEL
xoq/__init__.py
xoq/__init__.pyi
xoq/py.typed
xoq/xoq.abi3.so
xoq-0.2.0.dist-info/RECORD
